WaterScenes/Config.py
WaterScenes/DataLoader.py
WaterScenes/Transformation.py
WaterScenes/WaterScenes.py
WaterScenes/__init__.py
WaterScenes/api.py
WaterScenes-1.0.8.dist-info/METADATA
WaterScenes-1.0.8.dist-info/WHEEL
WaterScenes-1.0.8.dist-info/top_level.txt
WaterScenes-1.0.8.dist-info/RECORD
