Metadata-Version: 2.1
Name: WaterScenes
Version: 1.0.8
Summary: Toolkit for WaterScenes
Home-page: https://github.com/waterscenes
Author: Shanliang Yao
Author-email: shanliang.yao19@gmail.com
License: MIT-0
Requires-Python: >=3.8
Requires-Dist: numpy
